README
setup.py
hgversion/__init__.py
hgversion/hgvers.py
hgversion/hgversion.py
hgversion.egg-info/PKG-INFO
hgversion.egg-info/SOURCES.txt
hgversion.egg-info/dependency_links.txt
hgversion.egg-info/top_level.txt