Metadata-Version: 1.0
Name: hgversion
Version: 0.1.8
Summary: automatic version generator from a mercurial repository
Home-page: http://limedav.com/hg/hgversion/
Author: Tim Olsen
Author-email: tolsen@limespot.com
License: Apache 2.0
Keywords: mercurial hg version
Platform: UNKNOWN
Classifier: Development Status :: 3 - Alpha
Classifier: Intended Audience :: Developers
Classifier: License :: OSI Approved :: Apache Software License
Classifier: Programming Language :: Python
Classifier: Topic :: Software Development :: Libraries
Classifier: Topic :: Software Development :: Libraries :: Python Modules
Classifier: Topic :: Software Development :: Version Control
